<annotation>
	<folder>XML</folder>
	<filename>img268.jpg</filename>
	<path>C:\Users\kurtz\Documents\ENSEEIHT3A\IA\deep-learning-3A\animals-master\labelled\img268.jpg</path>
	<source>
		<database>Unknown</database>
	</source>
	<size>
		<width>64</width>
		<height>64</height>
		<depth>3</depth>
	</size>
	<segmented>0</segmented>
	<object>
		<name>guépard</name>
		<pose>Unspecified</pose>
		<truncated>0</truncated>
		<difficult>0</difficult>
		<bndbox>
			<xmin>26</xmin>
			<ymin>4</ymin>
			<xmax>50</xmax>
			<ymax>62</ymax>
		</bndbox>
	</object>
	<object>
		<name>guépard</name>
		<pose>Unspecified</pose>
		<truncated>0</truncated>
		<difficult>0</difficult>
		<bndbox>
			<xmin>8</xmin>
			<ymin>24</ymin>
			<xmax>28</xmax>
			<ymax>63</ymax>
		</bndbox>
	</object>
</annotation>
