<annotation>
	<folder>XML</folder>
	<filename>img475.jpg</filename>
	<path>C:\Users\kurtz\Documents\ENSEEIHT3A\IA\deep-learning-3A\animals-master\labelled\img475.jpg</path>
	<source>
		<database>Unknown</database>
	</source>
	<size>
		<width>64</width>
		<height>64</height>
		<depth>3</depth>
	</size>
	<segmented>0</segmented>
	<object>
		<name>orang-outan</name>
		<pose>Unspecified</pose>
		<truncated>0</truncated>
		<difficult>0</difficult>
		<bndbox>
			<xmin>9</xmin>
			<ymin>15</ymin>
			<xmax>26</xmax>
			<ymax>54</ymax>
		</bndbox>
	</object>
	<object>
		<name>orang-outan</name>
		<pose>Unspecified</pose>
		<truncated>0</truncated>
		<difficult>0</difficult>
		<bndbox>
			<xmin>28</xmin>
			<ymin>2</ymin>
			<xmax>51</xmax>
			<ymax>62</ymax>
		</bndbox>
	</object>
</annotation>
